extcolors/__init__.py
extcolors/command.py
extcolors/conversion.py
extcolors/difference.py
extcolors-1.0.0.dist-info/LICENSE
extcolors-1.0.0.dist-info/METADATA
extcolors-1.0.0.dist-info/WHEEL
extcolors-1.0.0.dist-info/entry_points.txt
extcolors-1.0.0.dist-info/top_level.txt
extcolors-1.0.0.dist-info/RECORD
