Metadata-Version: 2.1
Name: extcolors
Version: 1.0.0
Summary: Extract colors from an image. Colors are grouped based on visual similarities using the CIE76 formula.
Home-page: https://github.com/CairX/extract-colors-py
Author: CairX
Author-email: lazycairx@gmail.com
License: MIT
Keywords: extract colors image
Platform: UNKNOWN
Classifier: Development Status :: 3 - Alpha
Classifier: Intended Audience :: Developers
Classifier: License :: OSI Approved :: MIT License
Classifier: Natural Language :: English
Classifier: Environment :: Console
Classifier: Topic :: Multimedia :: Graphics
Classifier: Topic :: Software Development :: Libraries :: Python Modules
Classifier: Topic :: Utilities
Classifier: Programming Language :: Python :: 3
Classifier: Programming Language :: Python :: 3.6
Classifier: Programming Language :: Python :: 3.7
Classifier: Programming Language :: Python :: 3.8
Classifier: Programming Language :: Python :: 3.9
Classifier: Programming Language :: Python :: 3 :: Only
Requires-Python: >=3.6
Provides-Extra: dev
